MANIFEST.in
README.rst
setup.cfg
setup.py
pyprf/__init__.py
pyprf.egg-info/PKG-INFO
pyprf.egg-info/SOURCES.txt
pyprf.egg-info/dependency_links.txt
pyprf.egg-info/entry_points.txt
pyprf.egg-info/requires.txt
pyprf.egg-info/top_level.txt
pyprf/analysis/__init__.py
pyprf/analysis/__main__.py
pyprf/analysis/cython_leastsquares.c
pyprf/analysis/cython_leastsquares.pyx
pyprf/analysis/cython_leastsquares_two.c
pyprf/analysis/cython_leastsquares_two.pyx
pyprf/analysis/cython_prf_convolve.c
pyprf/analysis/cython_prf_convolve.pyx
pyprf/analysis/find_prf.py
pyprf/analysis/find_prf_cpu.py
pyprf/analysis/find_prf_cpu_hdf5.py
pyprf/analysis/find_prf_gpu.py
pyprf/analysis/load_config.py
pyprf/analysis/model_creation_load_png.py
pyprf/analysis/model_creation_main.py
pyprf/analysis/model_creation_pixelwise.py
pyprf/analysis/model_creation_pixelwise_par.py
pyprf/analysis/model_creation_timecourses.py
pyprf/analysis/model_creation_timecourses_par.py
pyprf/analysis/nii_to_hdf5.py
pyprf/analysis/preprocessing_hdf5.py
pyprf/analysis/preprocessing_main.py
pyprf/analysis/preprocessing_par.py
pyprf/analysis/pyprf_main.py
pyprf/analysis/utilities.py