Metadata-Version: 1.1
Name: pyprf
Version: 2.0.0
Summary: A free & open source python tool for population receptive                     field analysis of fMRI data.
Home-page: https://github.com/ingo-m/pyprf
Author: Ingo Marquardt
Author-email: ingo.marquardt@gmx.de
License: GNU General Public License Version 3
Download-URL: https://github.com/ingo-m/pyprf/archive/v2.0.0.tar.gz
Keywords: pRF,fMRI,retinotopy
Platform: UNKNOWN
